README.md
setup.py
mountcontrol/__init__.py
mountcontrol/alignStar.py
mountcontrol/connection.py
mountcontrol/convert.py
mountcontrol/firmware.py
mountcontrol/geometry.py
mountcontrol/model.py
mountcontrol/modelStar.py
mountcontrol/mount.py
mountcontrol/obsSite.py
mountcontrol/qtmount.py
mountcontrol/satellite.py
mountcontrol/setting.py
mountcontrol_arm.egg-info/PKG-INFO
mountcontrol_arm.egg-info/SOURCES.txt
mountcontrol_arm.egg-info/dependency_links.txt
mountcontrol_arm.egg-info/requires.txt
mountcontrol_arm.egg-info/top_level.txt
mountcontrol_arm.egg-info/zip-safe