Metadata-Version: 1.2
Name: mountcontrol-arm
Version: 0.133
Summary: tooling for a 10micron mount
Home-page: https://github.com/mworion/MountWizzard4
Author: mworion
Author-email: michael@wuertenberger.org
License: APL 2.0
Platform: UNKNOWN
Classifier: Development Status :: 3 - Alpha
Classifier: Programming Language :: Python :: 3.7
Classifier: Operating System :: OS Independent
Classifier: Topic :: Utilities
Classifier: License :: OSI Approved :: Apache Software License
Requires-Python: >=3.7.2
